aisuiteplus/__init__.py
aisuiteplus/client.py
aisuiteplus/provider.py
aisuiteplus/framework/__init__.py
aisuiteplus/framework/chat_completion_response.py
aisuiteplus/framework/choice.py
aisuiteplus/framework/function_call.py
aisuiteplus/framework/message.py
aisuiteplus/framework/provider_interface.py
aisuiteplus/providers/__init__.py
aisuiteplus/providers/anthropic_provider.py
aisuiteplus/providers/aws_provider.py
aisuiteplus/providers/azure_provider.py
aisuiteplus/providers/cohere_provider.py
aisuiteplus/providers/fireworks_provider.py
aisuiteplus/providers/google_provider.py
aisuiteplus/providers/groq_provider.py
aisuiteplus/providers/huggingface_provider.py
aisuiteplus/providers/mistral_provider.py
aisuiteplus/providers/ollama_provider.py
aisuiteplus/providers/openai_provider.py
aisuiteplus/providers/sambanova_provider.py
aisuiteplus/providers/together_provider.py
aisuiteplus/providers/watsonx_provider.py
aisuiteplus/providers/xai_provider.py
aisuiteplus-0.1.6.dist-info/METADATA
aisuiteplus-0.1.6.dist-info/WHEEL
aisuiteplus-0.1.6.dist-info/licenses/LICENSE
aisuiteplus-0.1.6.dist-info/RECORD
