Metadata-Version: 2.4
Name: aisuiteplus
Version: 0.1.6
Summary: Uniform access layer for LLMs
Project-URL: Homepage, https://github.com/Vikramardham/aisuiteplus
Project-URL: Bug Tracker, https://github.com/Vikramardham/aisuiteplus/issues
Author-email: Vikram A <vikram@butterflai.com>
License-File: LICENSE
Requires-Python: >=3.11
Requires-Dist: anthropic>=0.42.0
Requires-Dist: build>=1.2.2.post1
Requires-Dist: deepeval>=2.0.9
Requires-Dist: hatchling>=1.27.0
Requires-Dist: ipykernel>=6.29.5
Requires-Dist: load-dotenv>=0.1.0
Requires-Dist: loguru>=0.7.3
Requires-Dist: openai>=1.58.1
Requires-Dist: openpyxl>=3.1.5
Requires-Dist: pypdf2>=3.0.1
Requires-Dist: pytest-cov>=6.0.0
Requires-Dist: pytest>=8.3.4
Requires-Dist: twine>=6.0.1
Provides-Extra: all
Requires-Dist: anthropic>=0.30.1; extra == 'all'
Requires-Dist: boto3>=1.34.144; extra == 'all'
Requires-Dist: cohere>=5.12.0; extra == 'all'
Requires-Dist: groq>=0.9.0; extra == 'all'
Requires-Dist: ibm-watsonx-ai>=1.1.16; extra == 'all'
Requires-Dist: mistralai>=1.0.3; extra == 'all'
Requires-Dist: openai>=1.35.8; extra == 'all'
Requires-Dist: vertexai>=1.63.0; extra == 'all'
Provides-Extra: anthropic
Requires-Dist: anthropic>=0.30.1; extra == 'anthropic'
Provides-Extra: aws
Requires-Dist: boto3>=1.34.144; extra == 'aws'
Provides-Extra: azure
Provides-Extra: cohere
Requires-Dist: cohere>=5.12.0; extra == 'cohere'
Provides-Extra: dev
Requires-Dist: black>=24.4.2; extra == 'dev'
Requires-Dist: chromadb>=0.5.4; extra == 'dev'
Requires-Dist: datasets>=2.20.0; extra == 'dev'
Requires-Dist: fireworks-ai>=0.14.0; extra == 'dev'
Requires-Dist: ipykernel>=6.29.5; extra == 'dev'
Requires-Dist: notebook>=7.2.1; extra == 'dev'
Requires-Dist: ollama>=0.2.1; extra == 'dev'
Requires-Dist: pre-commit>=3.7.1; extra == 'dev'
Requires-Dist: python-dotenv>=1.0.1; extra == 'dev'
Requires-Dist: sentence-transformers>=3.0.1; extra == 'dev'
Provides-Extra: google
Requires-Dist: vertexai>=1.63.0; extra == 'google'
Provides-Extra: groq
Requires-Dist: groq>=0.9.0; extra == 'groq'
Provides-Extra: huggingface
Provides-Extra: mistral
Requires-Dist: mistralai>=1.0.3; extra == 'mistral'
Provides-Extra: ollama
Provides-Extra: openai
Requires-Dist: openai>=1.35.8; extra == 'openai'
Provides-Extra: test
Requires-Dist: pytest-cov>=6.0.0; extra == 'test'
Requires-Dist: pytest>=8.2.2; extra == 'test'
Provides-Extra: watsonx
Requires-Dist: ibm-watsonx-ai>=1.1.16; extra == 'watsonx'
